contactList/VERSION
contactList/__init__.py
contactList/entry.py
contactList/arguments/__init__.py
contactList/arguments/top.py
contactList/arguments/base/__init__.py
contactList/arguments/base/abstract.py
contactList/arguments/base/exception.py
contactList/arguments/base/tree.py
contactList/arguments/base/tests/__init__.py
contactList/arguments/base/tests/testCommandTree.py
contactList/arguments/cluster/__init__.py
contactList/arguments/cluster/add.py
contactList/arguments/cluster/cluster.py
contactList/arguments/cluster/rm.py
contactList/arguments/cluster/tests/__init__.py
contactList/arguments/cluster/tests/testCluster.py
contactList/arguments/cluster/tests/testClusterAdd.py
contactList/arguments/cluster/tests/testClusterRm.py
contactList/arguments/email/__init__.py
contactList/arguments/email/add.py
contactList/arguments/email/email.py
contactList/arguments/email/rm.py
contactList/arguments/email/tests/__init__.py
contactList/arguments/email/tests/testEmail.py
contactList/arguments/email/tests/testEmailAdd.py
contactList/arguments/email/tests/testEmailRm.py
contactList/arguments/group/__init__.py
contactList/arguments/group/add.py
contactList/arguments/group/group.py
contactList/arguments/group/rm.py
contactList/arguments/group/tests/__init__.py
contactList/arguments/group/tests/testGroup.py
contactList/arguments/group/tests/testGroupAdd.py
contactList/arguments/group/tests/testGroupRm.py
contactList/arguments/tests/__init__.py
contactList/arguments/tests/testParseTop.py
contactList/contacts/__init__.py
contactList/contacts/contact.py
contactList/contacts/base/__init__.py
contactList/contacts/base/abstract.py
contactList/contacts/base/data.py
contactList/contacts/base/exception.py
contactList/contacts/base/tests/__init__.py
contactList/contacts/base/tests/testContactValidation.py
contactList/contacts/base/tests/testEmailList.py
contactList/contacts/cluster/__init__.py
contactList/contacts/cluster/operation.py
contactList/contacts/cluster/tests/__init__.py
contactList-0.1.0.dist-info/entry_points.txt
contactList-0.1.0.dist-info/LICENSE
contactList-0.1.0.dist-info/WHEEL
contactList-0.1.0.dist-info/METADATA
contactList-0.1.0.dist-info/RECORD
