Metadata-Version: 2.1
Name: contactList
Version: 0.1.0
Summary: A Python 3 framework for constructing, managing and organising email addresses in YAML format.
Home-page: https://gitlab.com/blueskyjunkie/contactlist
License: UNKNOWN
Keywords: email contacts yaml
Author: Russell Smiley
Author-email: im.russell.smiley@gmail.com
Requires-Python: >=3.6
Classifier: License :: OSI Approved :: GNU General Public License v3 or later (GPLv3+)
Requires-Dist: pyyaml
Requires-Dist: nose; extra == "dev"
Requires-Dist: nose-cov; extra == "dev"
Requires-Dist: nosehtmloutput-2; extra == "dev"
Provides-Extra: .none
Provides-Extra: dev
